[
    {
        "match_id": "UyFRK2OE",
        "tournament": "M15 Kursumlijska Banja 4 (Serbia), clay",
        "ground": "Clay",
        "date_text": "12.06. 12:00",
        "home_player": "D'Agostino S.",
        "away_player": "Giraldi C.",
        "home_score": 2,
        "away_score": 1,
        "winner": "home",
        "set_scores": [
            {
                "home": "7",
                "away": "6"
            },
            {
                "home": "6",
                "away": "7"
            },
            {
                "home": "6",
                "away": "2"
            }
        ],
        "date": "2026-06-12"
    },
    {
        "match_id": "nJMpqI5t",
        "tournament": "M15 Kursumlijska Banja 4 (Serbia), clay",
        "ground": "Clay",
        "date_text": "11.06. 10:00\nRetired",
        "home_player": "Giraldi C.",
        "away_player": "Vincent Ruggeri S.",
        "home_score": 1,
        "away_score": 0,
        "winner": "home",
        "set_scores": [
            {
                "home": "6",
                "away": "2"
            },
            {
                "home": "3",
                "away": "0"
            }
        ],
        "date": "2026-06-11"
    },
    {
        "match_id": "OfCrkaZF",
        "tournament": "M15 Kursumlijska Banja 4 (Serbia), clay",
        "ground": "Clay",
        "date_text": "10.06. 15:00",
        "home_player": "Giraldi C.",
        "away_player": "Vazquez F. A.",
        "home_score": 2,
        "away_score": 0,
        "winner": "home",
        "set_scores": [
            {
                "home": "6",
                "away": "0"
            },
            {
                "home": "6",
                "away": "1"
            }
        ],
        "date": "2026-06-10"
    },
    {
        "match_id": "YsNlgnZH",
        "tournament": "M15 Kursumlijska Banja 3 (Serbia), clay",
        "ground": "Clay",
        "date_text": "03.06. 11:30",
        "home_player": "Pisaric A.",
        "away_player": "Giraldi C.",
        "home_score": 2,
        "away_score": 0,
        "winner": "home",
        "set_scores": [
            {
                "home": "6",
                "away": "2"
            },
            {
                "home": "6",
                "away": "3"
            }
        ],
        "date": "2026-06-03"
    },
    {
        "match_id": "xfMLTp9e",
        "tournament": "M25 Kursumlijska Banja (Serbia), clay",
        "ground": "Clay",
        "date_text": "27.05. 13:15",
        "home_player": "Vasilev A.",
        "away_player": "Giraldi C.",
        "home_score": 2,
        "away_score": 0,
        "winner": "home",
        "set_scores": [
            {
                "home": "6",
                "away": "1"
            },
            {
                "home": "6",
                "away": "1"
            }
        ],
        "date": "2026-05-27"
    },
    {
        "match_id": "t44NaPr1",
        "tournament": "M15 Kursumlijska Banja 2 (Serbia), clay",
        "ground": "Clay",
        "date_text": "20.05. 13:00",
        "home_player": "Giraldi C.",
        "away_player": "Jovic N.",
        "home_score": 0,
        "away_score": 2,
        "winner": "away",
        "set_scores": [
            {
                "home": "2",
                "away": "6"
            },
            {
                "home": "4",
                "away": "6"
            }
        ],
        "date": "2026-05-20"
    },
    {
        "match_id": "IJp6cL46",
        "tournament": "M25 Castelldefels (Spain), clay",
        "ground": "Clay",
        "date_text": "30.04. 13:30",
        "home_player": "Giraldi C.",
        "away_player": "Perez Contri S.",
        "home_score": 0,
        "away_score": 2,
        "winner": "away",
        "set_scores": [
            {
                "home": "0",
                "away": "6"
            },
            {
                "home": "2",
                "away": "6"
            }
        ],
        "date": "2026-04-30"
    },
    {
        "match_id": "08eYrPak",
        "tournament": "M25 Castelldefels (Spain), clay",
        "ground": "Clay",
        "date_text": "29.04. 12:00",
        "home_player": "Giraldi C.",
        "away_player": "Cekirge K.",
        "home_score": 2,
        "away_score": 0,
        "winner": "home",
        "set_scores": [
            {
                "home": "7",
                "away": "6"
            },
            {
                "home": "6",
                "away": "0"
            }
        ],
        "date": "2026-04-29"
    },
    {
        "match_id": "n38e6PpJ",
        "tournament": "M15 Sanxenxo (Spain), hard",
        "ground": "Hard",
        "date_text": "21.04. 12:00",
        "home_player": "Giraldi C.",
        "away_player": "Van Herck L.",
        "home_score": 0,
        "away_score": 2,
        "winner": "away",
        "set_scores": [
            {
                "home": "4",
                "away": "6"
            },
            {
                "home": "4",
                "away": "6"
            }
        ],
        "date": "2026-04-21"
    },
    {
        "match_id": "ABjIRRF7",
        "tournament": "M15 Ceuta (Spain), hard",
        "ground": "Hard",
        "date_text": "14.04. 15:00",
        "home_player": "Giraldi C.",
        "away_player": "Lalami Laaroussi Y.",
        "home_score": 0,
        "away_score": 2,
        "winner": "away",
        "set_scores": [
            {
                "home": "2",
                "away": "6"
            },
            {
                "home": "1",
                "away": "6"
            }
        ],
        "date": "2026-04-14"
    },
    {
        "match_id": "SWOqPSCE",
        "tournament": "M25 Badalona (Spain), clay",
        "ground": "Clay",
        "date_text": "18.03. 15:35",
        "home_player": "Cordoba C.",
        "away_player": "Giraldi C.",
        "home_score": 2,
        "away_score": 0,
        "winner": "home",
        "set_scores": [
            {
                "home": "6",
                "away": "3"
            },
            {
                "home": "6",
                "away": "3"
            }
        ],
        "date": "2026-03-18"
    },
    {
        "match_id": "8A5DxEKE",
        "tournament": "M15 Madrid (Spain), clay",
        "ground": "Clay",
        "date_text": "03.09.2025",
        "home_player": "Mazdrashki A.",
        "away_player": "Giraldi C.",
        "home_score": 2,
        "away_score": 0,
        "winner": "home",
        "set_scores": [
            {
                "home": "6",
                "away": "3"
            },
            {
                "home": "6",
                "away": "3"
            }
        ],
        "date": "2025-09-03"
    },
    {
        "match_id": "MRG6N5Er",
        "tournament": "M25 Gijon (Spain), clay",
        "ground": "Clay",
        "date_text": "12.08.2025",
        "home_player": "Giraldi C.",
        "away_player": "Perez Contri S.",
        "home_score": 0,
        "away_score": 2,
        "winner": "away",
        "set_scores": [
            {
                "home": "4",
                "away": "6"
            },
            {
                "home": "2",
                "away": "6"
            }
        ],
        "date": "2025-08-12"
    },
    {
        "match_id": "h0xwkRkJ",
        "tournament": "M25+H Tauste (Spain), hard",
        "ground": "Hard",
        "date_text": "05.08.2025",
        "home_player": "McKennon M.",
        "away_player": "Giraldi C.",
        "home_score": 2,
        "away_score": 1,
        "winner": "home",
        "set_scores": [
            {
                "home": "6",
                "away": "2"
            },
            {
                "home": "4",
                "away": "6"
            },
            {
                "home": "6",
                "away": "1"
            }
        ],
        "date": "2025-08-05"
    },
    {
        "match_id": "b3QdnjVa",
        "tournament": "M25 Kramsach (Austria), clay",
        "ground": "Clay",
        "date_text": "15.07.2025",
        "home_player": "Tanner G. L.",
        "away_player": "Giraldi C.",
        "home_score": 2,
        "away_score": 0,
        "winner": "home",
        "set_scores": [
            {
                "home": "7",
                "away": "6"
            },
            {
                "home": "6",
                "away": "2"
            }
        ],
        "date": "2025-07-15"
    },
    {
        "match_id": "0Wt1eszi",
        "tournament": "M15 Kursumlijska Banja 4 (Serbia), clay",
        "ground": "Clay",
        "date_text": "22.05.2025",
        "home_player": "Marino P.",
        "away_player": "Giraldi C.",
        "home_score": 2,
        "away_score": 0,
        "winner": "home",
        "set_scores": [
            {
                "home": "6",
                "away": "3"
            },
            {
                "home": "6",
                "away": "3"
            }
        ],
        "date": "2025-05-22"
    },
    {
        "match_id": "Szv9DEyp",
        "tournament": "M15 Kursumlijska Banja 4 (Serbia), clay",
        "ground": "Clay",
        "date_text": "21.05.2025",
        "home_player": "Giraldi C.",
        "away_player": "Srbljak G.",
        "home_score": 2,
        "away_score": 0,
        "winner": "home",
        "set_scores": [
            {
                "home": "6",
                "away": "4"
            },
            {
                "home": "6",
                "away": "3"
            }
        ],
        "date": "2025-05-21"
    },
    {
        "match_id": "fZVDNqnn",
        "tournament": "M15 Kursumlijska Banja 3 (Serbia), clay",
        "ground": "Clay",
        "date_text": "14.05.2025",
        "home_player": "Giraldi C.",
        "away_player": "Misasi G.",
        "home_score": 0,
        "away_score": 2,
        "winner": "away",
        "set_scores": [
            {
                "home": "2",
                "away": "6"
            },
            {
                "home": "2",
                "away": "6"
            }
        ],
        "date": "2025-05-14"
    },
    {
        "match_id": "2HQye6fA",
        "tournament": "M25 Kursumlijska Banja (Serbia), clay",
        "ground": "Clay",
        "date_text": "07.05.2025",
        "home_player": "Zahraj P.",
        "away_player": "Giraldi C.",
        "home_score": 2,
        "away_score": 0,
        "winner": "home",
        "set_scores": [
            {
                "home": "6",
                "away": "3"
            },
            {
                "home": "6",
                "away": "1"
            }
        ],
        "date": "2025-05-07"
    },
    {
        "match_id": "ILl8z3aC",
        "tournament": "M25 Badalona (Spain), clay",
        "ground": "Clay",
        "date_text": "20.03.2025",
        "home_player": "Giraldi C.",
        "away_player": "Cervantes Tomas L.",
        "home_score": 0,
        "away_score": 2,
        "winner": "away",
        "set_scores": [
            {
                "home": "4",
                "away": "6"
            },
            {
                "home": "0",
                "away": "6"
            }
        ],
        "date": "2025-03-20"
    },
    {
        "match_id": "vBwht5io",
        "tournament": "M25 Zaragoza (Spain), clay",
        "ground": "Clay",
        "date_text": "02.10.2024",
        "home_player": "Giraldi C.",
        "away_player": "Demin Y.",
        "home_score": 0,
        "away_score": 2,
        "winner": "away",
        "set_scores": [
            {
                "home": "3",
                "away": "6"
            },
            {
                "home": "5",
                "away": "7"
            }
        ],
        "date": "2024-10-02"
    },
    {
        "match_id": "GlhcI2jA",
        "tournament": "M15 Cap d'Agde (France), clay",
        "ground": "Clay",
        "date_text": "27.08.2024",
        "home_player": "Camus C.",
        "away_player": "Giraldi C.",
        "home_score": 2,
        "away_score": 0,
        "winner": "home",
        "set_scores": [
            {
                "home": "7",
                "away": "6"
            },
            {
                "home": "6",
                "away": "3"
            }
        ],
        "date": "2024-08-27"
    },
    {
        "match_id": "tG1nfNzi",
        "tournament": "M25 Santander (Spain), clay",
        "ground": "Clay",
        "date_text": "20.08.2024",
        "home_player": "Giraldi C.",
        "away_player": "Alvarez Sarmiento M. L.",
        "home_score": 0,
        "away_score": 2,
        "winner": "away",
        "set_scores": [
            {
                "home": "0",
                "away": "6"
            },
            {
                "home": "2",
                "away": "6"
            }
        ],
        "date": "2024-08-20"
    },
    {
        "match_id": "Yq9eu30E",
        "tournament": "M15 Gijon (Spain), clay",
        "ground": "Clay",
        "date_text": "14.08.2024",
        "home_player": "Giraldi C.",
        "away_player": "Perez Contri S.",
        "home_score": 0,
        "away_score": 2,
        "winner": "away",
        "set_scores": [
            {
                "home": "2",
                "away": "6"
            },
            {
                "home": "2",
                "away": "6"
            }
        ],
        "date": "2024-08-14"
    },
    {
        "match_id": "8Wtj3ibl",
        "tournament": "M15 Gijon (Spain), clay",
        "ground": "Clay",
        "date_text": "12.08.2024",
        "home_player": "Giraldi C.",
        "away_player": "De Felipe Garcia S.",
        "home_score": 2,
        "away_score": 0,
        "winner": "home",
        "set_scores": [
            {
                "home": "6",
                "away": "4"
            },
            {
                "home": "6",
                "away": "2"
            }
        ],
        "date": "2024-08-12"
    },
    {
        "match_id": "xUaaRJXp",
        "tournament": "M25 Roda de Bara (Spain), hard",
        "ground": "Hard",
        "date_text": "10.07.2024",
        "home_player": "Giraldi C.",
        "away_player": "Fernandez Flores D.",
        "home_score": 0,
        "away_score": 2,
        "winner": "away",
        "set_scores": [
            {
                "home": "4",
                "away": "6"
            },
            {
                "home": "2",
                "away": "6"
            }
        ],
        "date": "2024-07-10"
    },
    {
        "match_id": "Y92kP1Yi",
        "tournament": "M15 Kursumlijska Banja 8 (Serbia), clay",
        "ground": "Clay",
        "date_text": "21.06.2024",
        "home_player": "Giraldi C.",
        "away_player": "Pavlovic L.",
        "home_score": 0,
        "away_score": 2,
        "winner": "away",
        "set_scores": [
            {
                "home": "3",
                "away": "6"
            },
            {
                "home": "1",
                "away": "6"
            }
        ],
        "date": "2024-06-21"
    },
    {
        "match_id": "ruST063j",
        "tournament": "M15 Kursumlijska Banja 8 (Serbia), clay",
        "ground": "Clay",
        "date_text": "20.06.2024",
        "home_player": "Bassem Sobhy M.",
        "away_player": "Giraldi C.",
        "home_score": 1,
        "away_score": 2,
        "winner": "away",
        "set_scores": [
            {
                "home": "6",
                "away": "4"
            },
            {
                "home": "5",
                "away": "7"
            },
            {
                "home": "1",
                "away": "6"
            }
        ],
        "date": "2024-06-20"
    },
    {
        "match_id": "82oyHSE4",
        "tournament": "M15 Kursumlijska Banja 8 (Serbia), clay",
        "ground": "Clay",
        "date_text": "19.06.2024",
        "home_player": "Giraldi C.",
        "away_player": "Jankanj V.",
        "home_score": 2,
        "away_score": 0,
        "winner": "home",
        "set_scores": [
            {
                "home": "6",
                "away": "3"
            },
            {
                "home": "6",
                "away": "3"
            }
        ],
        "date": "2024-06-19"
    },
    {
        "match_id": "4KLElOGs",
        "tournament": "M15 Kursumlijska Banja 6 (Serbia), clay",
        "ground": "Clay",
        "date_text": "29.05.2024",
        "home_player": "Giraldi C.",
        "away_player": "Srbljak G.",
        "home_score": 1,
        "away_score": 2,
        "winner": "away",
        "set_scores": [
            {
                "home": "7",
                "away": "5"
            },
            {
                "home": "5",
                "away": "7"
            },
            {
                "home": "0",
                "away": "6"
            }
        ],
        "date": "2024-05-29"
    },
    {
        "match_id": "8CSN3Ccj",
        "tournament": "M15 Antalya 2 (Turkey), clay",
        "ground": "Clay",
        "date_text": "18.01.2023",
        "home_player": "Barrena A.",
        "away_player": "Giraldi C.",
        "home_score": 2,
        "away_score": 0,
        "winner": "home",
        "set_scores": [
            {
                "home": "6",
                "away": "1"
            },
            {
                "home": "6",
                "away": "1"
            }
        ],
        "date": "2023-01-18"
    },
    {
        "match_id": "4Qlt4s0S",
        "tournament": "M15 Melilla (Spain), clay",
        "ground": "Clay",
        "date_text": "21.09.2022",
        "home_player": "Alcala Gurri M.",
        "away_player": "Giraldi C.",
        "home_score": 2,
        "away_score": 0,
        "winner": "home",
        "set_scores": [
            {
                "home": "6",
                "away": "1"
            },
            {
                "home": "6",
                "away": "0"
            }
        ],
        "date": "2022-09-21"
    }
]