[
    {
        "match_id": "lfojUt7l",
        "tournament": "CHALLENGER MEN - SINGLES: Asuncion 2 (Paraguay) - Qualification, clay",
        "ground": "Clay",
        "date_text": "14.06. 21:30",
        "home_player": "Martinez T.",
        "away_player": "Loureiro J. V. C.",
        "home_score": 0,
        "away_score": 2,
        "winner": "away",
        "date": "2026-06-14"
    },
    {
        "match_id": "GleMT5Ws",
        "tournament": "M15 Brasilia (Brazil), clay",
        "ground": "Clay",
        "date_text": "12.06. 19:30",
        "home_player": "Villanueva G.",
        "away_player": "Loureiro J. V. C.",
        "home_score": 2,
        "away_score": 0,
        "winner": "home",
        "date": "2026-06-12"
    },
    {
        "match_id": "4hYpZD0M",
        "tournament": "M15 Brasilia (Brazil), clay",
        "ground": "Clay",
        "date_text": "11.06. 18:00",
        "home_player": "Tosetto R.",
        "away_player": "Loureiro J. V. C.",
        "home_score": 0,
        "away_score": 2,
        "winner": "away",
        "date": "2026-06-11"
    },
    {
        "match_id": "OzMJrW86",
        "tournament": "M15 Brasilia (Brazil), clay",
        "ground": "Clay",
        "date_text": "10.06. 17:30",
        "home_player": "Augusto dos Santos R.",
        "away_player": "Loureiro J. V. C.",
        "home_score": 1,
        "away_score": 2,
        "winner": "away",
        "date": "2026-06-10"
    },
    {
        "match_id": "CG2rTKAC",
        "tournament": "M25 Cuiaba (Brazil), clay",
        "ground": "Clay",
        "date_text": "03.06. 22:20",
        "home_player": "Pucinelli de Almeida M.",
        "away_player": "Loureiro J. V. C.",
        "home_score": 2,
        "away_score": 0,
        "winner": "home",
        "date": "2026-06-03"
    },
    {
        "match_id": "zo4XGkqd",
        "tournament": "M15 Maringa 2 (Brazil), clay",
        "ground": "Clay",
        "date_text": "19.05. 19:30",
        "home_player": "Loureiro J. V. C.",
        "away_player": "Giamichelle S.",
        "home_score": 1,
        "away_score": 2,
        "winner": "away",
        "date": "2026-05-19"
    },
    {
        "match_id": "fyMZSyPQ",
        "tournament": "M15 Maringa (Brazil), clay",
        "ground": "Clay",
        "date_text": "13.05. 23:00",
        "home_player": "De Almeida Santos P. A.",
        "away_player": "Loureiro J. V. C.",
        "home_score": 2,
        "away_score": 1,
        "winner": "home",
        "date": "2026-05-13"
    },
    {
        "match_id": "8vhFox96",
        "tournament": "Santos (Brazil) - Qualification, clay",
        "ground": "Clay",
        "date_text": "05.05. 16:40",
        "home_player": "Zanellato N.",
        "away_player": "Loureiro J. V. C.",
        "home_score": 2,
        "away_score": 0,
        "winner": "home",
        "date": "2026-05-05"
    },
    {
        "match_id": "YZ2SNxBs",
        "tournament": "Santos (Brazil) - Qualification, clay",
        "ground": "Clay",
        "date_text": "04.05. 16:40",
        "home_player": "Pucinelli De Almeida R.",
        "away_player": "Loureiro J. V. C.",
        "home_score": 0,
        "away_score": 2,
        "winner": "away",
        "date": "2026-05-04"
    },
    {
        "match_id": "GUGaka4s",
        "tournament": "Campinas (Brazil) - Qualification, clay",
        "ground": "Clay",
        "date_text": "05.04. 16:10",
        "home_player": "De La Fuente S.",
        "away_player": "Loureiro J. V. C.",
        "home_score": 2,
        "away_score": 0,
        "winner": "home",
        "date": "2026-04-05"
    },
    {
        "match_id": "ULCNvGZg",
        "tournament": "Sao Leopoldo (Brazil) - Qualification, clay",
        "ground": "Clay",
        "date_text": "29.03. 17:10",
        "home_player": "Loureiro J. V. C.",
        "away_player": "Torrealba B.",
        "home_score": 0,
        "away_score": 2,
        "winner": "away",
        "date": "2026-03-29"
    },
    {
        "match_id": "MDfeWYtS",
        "tournament": "Bucaramanga 2 (Colombia) - Qualification, clay",
        "ground": "Clay",
        "date_text": "23.03. 20:05",
        "home_player": "Loureiro J. V. C.",
        "away_player": "George B. T.",
        "home_score": 0,
        "away_score": 2,
        "winner": "away",
        "date": "2026-03-23"
    },
    {
        "match_id": "vyCfVF5l",
        "tournament": "Bucaramanga 2 (Colombia) - Qualification, clay",
        "ground": "Clay",
        "date_text": "23.03. 01:00",
        "home_player": "Loureiro J. V. C.",
        "away_player": "Kleiman M.",
        "home_score": 2,
        "away_score": 0,
        "winner": "home",
        "date": "2026-03-23"
    },
    {
        "match_id": "2H5EoVEk",
        "tournament": "M15 Montreal (Canada), hard (indoor)",
        "ground": "Hard",
        "date_text": "11.03. 21:30",
        "home_player": "Loureiro J. V. C.",
        "away_player": "Gurenko V.",
        "home_score": 1,
        "away_score": 2,
        "winner": "away",
        "date": "2026-03-11"
    },
    {
        "match_id": "6e1XrEg4",
        "tournament": "M15 Sherbrooke (Canada), hard (indoor)",
        "ground": "Hard",
        "date_text": "05.03. 19:00",
        "home_player": "Kirchheimer S.",
        "away_player": "Loureiro J. V. C.",
        "home_score": 2,
        "away_score": 1,
        "winner": "home",
        "date": "2026-03-05"
    },
    {
        "match_id": "ncBYpB0C",
        "tournament": "M15 Sherbrooke (Canada), hard (indoor)",
        "ground": "Hard",
        "date_text": "03.03. 22:30",
        "home_player": "Loureiro J. V. C.",
        "away_player": "Van Noord N. P.",
        "home_score": 2,
        "away_score": 1,
        "winner": "home",
        "date": "2026-03-03"
    },
    {
        "match_id": "EaRLDC0G",
        "tournament": "M15 Naples, FL 3 (USA), clay",
        "ground": "Clay",
        "date_text": "24.02. 21:00",
        "home_player": "Bigun K.",
        "away_player": "Loureiro J. V. C.",
        "home_score": 2,
        "away_score": 0,
        "winner": "home",
        "date": "2026-02-24"
    },
    {
        "match_id": "fBvupSen",
        "tournament": "M15 Naples, FL 2 (USA), clay",
        "ground": "Clay",
        "date_text": "19.02. 18:00",
        "home_player": "Heck H.",
        "away_player": "Loureiro J. V. C.",
        "home_score": 2,
        "away_score": 0,
        "winner": "home",
        "date": "2026-02-19"
    },
    {
        "match_id": "vLueWgyq",
        "tournament": "M15 Naples, FL 2 (USA), clay",
        "ground": "Clay",
        "date_text": "17.02. 20:00\nRetired",
        "home_player": "Tenti F.",
        "away_player": "Loureiro J. V. C.",
        "home_score": 0,
        "away_score": 1,
        "winner": "away",
        "date": "2026-02-17"
    },
    {
        "match_id": "Ied1wToQ",
        "tournament": "M15 Sunrise, FL (USA), clay",
        "ground": "Clay",
        "date_text": "11.02. 19:30",
        "home_player": "Loureiro J. V. C.",
        "away_player": "Sperle J.",
        "home_score": 1,
        "away_score": 2,
        "winner": "away",
        "date": "2026-02-11"
    },
    {
        "match_id": "EeSI80AF",
        "tournament": "M15 Ribeirao Preto (Brazil), clay",
        "ground": "Clay",
        "date_text": "29.11.2025",
        "home_player": "Oliveira N.",
        "away_player": "Loureiro J. V. C.",
        "home_score": 2,
        "away_score": 1,
        "winner": "home",
        "date": "2025-11-29"
    },
    {
        "match_id": "d2hbHM6r",
        "tournament": "M15 Ribeirao Preto (Brazil), clay",
        "ground": "Clay",
        "date_text": "28.11.2025",
        "home_player": "Loureiro J. V. C.",
        "away_player": "Camargo Lima E.",
        "home_score": 2,
        "away_score": 0,
        "winner": "home",
        "date": "2025-11-28"
    },
    {
        "match_id": "n37us0d2",
        "tournament": "M15 Ribeirao Preto (Brazil), clay",
        "ground": "Clay",
        "date_text": "27.11.2025",
        "home_player": "Loureiro J. V. C.",
        "away_player": "Garla F.",
        "home_score": 2,
        "away_score": 0,
        "winner": "home",
        "date": "2025-11-27"
    },
    {
        "match_id": "n3goudwe",
        "tournament": "M15 Ribeirao Preto (Brazil), clay",
        "ground": "Clay",
        "date_text": "26.11.2025",
        "home_player": "Loureiro J. V. C.",
        "away_player": "Batagin G.",
        "home_score": 2,
        "away_score": 1,
        "winner": "home",
        "date": "2025-11-26"
    },
    {
        "match_id": "GdGvoGzg",
        "tournament": "Florianopolis (Brazil) - Qualification, clay",
        "ground": "Clay",
        "date_text": "16.11.2025",
        "home_player": "Loureiro J. V. C.",
        "away_player": "Wendler Filho J.",
        "home_score": 0,
        "away_score": 2,
        "winner": "away",
        "date": "2025-11-16"
    },
    {
        "match_id": "QgrrgEJ0",
        "tournament": "M15 Criciuma (Brazil), clay",
        "ground": "Clay",
        "date_text": "11.11.2025",
        "home_player": "Zanellato N.",
        "away_player": "Loureiro J. V. C.",
        "home_score": 2,
        "away_score": 1,
        "winner": "home",
        "date": "2025-11-11"
    },
    {
        "match_id": "v9l6f0OE",
        "tournament": "M25 Santa Cruz do Sul (Brazil), clay",
        "ground": "Clay",
        "date_text": "05.11.2025",
        "home_player": "Monferrer E.",
        "away_player": "Loureiro J. V. C.",
        "home_score": 2,
        "away_score": 0,
        "winner": "home",
        "date": "2025-11-05"
    },
    {
        "match_id": "fZROImEr",
        "tournament": "M15 Heraklion 9 (Greece), hard",
        "ground": "Hard",
        "date_text": "09.10.2025",
        "home_player": "Van Sambeek F.",
        "away_player": "Loureiro J. V. C.",
        "home_score": 2,
        "away_score": 1,
        "winner": "home",
        "date": "2025-10-09"
    },
    {
        "match_id": "rmWAlIkD",
        "tournament": "M15 Heraklion 9 (Greece), hard",
        "ground": "Hard",
        "date_text": "08.10.2025",
        "home_player": "Loureiro J. V. C.",
        "away_player": "Kountourakis I.",
        "home_score": 2,
        "away_score": 1,
        "winner": "home",
        "date": "2025-10-08"
    },
    {
        "match_id": "S4mbwWq9",
        "tournament": "M15 Heraklion 7 (Greece), hard",
        "ground": "Hard",
        "date_text": "24.09.2025",
        "home_player": "Bradshaw J.",
        "away_player": "Loureiro J. V. C.",
        "home_score": 2,
        "away_score": 1,
        "winner": "home",
        "date": "2025-09-24"
    },
    {
        "match_id": "YiPoP91K",
        "tournament": "M15 Melilla (Spain), clay",
        "ground": "Clay",
        "date_text": "21.09.2025",
        "home_player": "Loureiro J. V. C.",
        "away_player": "Vives Marcos P.",
        "home_score": 0,
        "away_score": 2,
        "winner": "away",
        "date": "2025-09-21"
    },
    {
        "match_id": "nkQ4gB2e",
        "tournament": "M15 Melilla (Spain), clay",
        "ground": "Clay",
        "date_text": "20.09.2025",
        "home_player": "Loureiro J. V. C.",
        "away_player": "Turriziani Alvarez A.",
        "home_score": 2,
        "away_score": 0,
        "winner": "home",
        "date": "2025-09-20"
    },
    {
        "match_id": "IRXcIuI5",
        "tournament": "M15 Melilla (Spain), clay",
        "ground": "Clay",
        "date_text": "19.09.2025",
        "home_player": "Gakhov I.",
        "away_player": "Loureiro J. V. C.",
        "home_score": 1,
        "away_score": 2,
        "winner": "away",
        "date": "2025-09-19"
    },
    {
        "match_id": "E9ilI6hA",
        "tournament": "M15 Melilla (Spain), clay",
        "ground": "Clay",
        "date_text": "18.09.2025",
        "home_player": "Loureiro J. V. C.",
        "away_player": "Juan Mano A.",
        "home_score": 2,
        "away_score": 0,
        "winner": "home",
        "date": "2025-09-18"
    },
    {
        "match_id": "nicYsyrh",
        "tournament": "M15 Melilla (Spain), clay",
        "ground": "Clay",
        "date_text": "17.09.2025",
        "home_player": "Carrascosa Diaz M.",
        "away_player": "Loureiro J. V. C.",
        "home_score": 1,
        "away_score": 2,
        "winner": "away",
        "date": "2025-09-17"
    },
    {
        "match_id": "d0iUqEM8",
        "tournament": "M15 Madrid 2 (Spain), hard",
        "ground": "Hard",
        "date_text": "12.09.2025",
        "home_player": "Hussey G.",
        "away_player": "Loureiro J. V. C.",
        "home_score": 2,
        "away_score": 0,
        "winner": "home",
        "date": "2025-09-12"
    },
    {
        "match_id": "OYczGvzG",
        "tournament": "M15 Madrid 2 (Spain), hard",
        "ground": "Hard",
        "date_text": "11.09.2025",
        "home_player": "Loureiro J. V. C.",
        "away_player": "Lagutin P.",
        "home_score": 2,
        "away_score": 0,
        "winner": "home",
        "date": "2025-09-11"
    },
    {
        "match_id": "zijPqKrm",
        "tournament": "M15 Madrid 2 (Spain), hard",
        "ground": "Hard",
        "date_text": "09.09.2025",
        "home_player": "Loureiro J. V. C.",
        "away_player": "Rodriguez R.",
        "home_score": 2,
        "away_score": 0,
        "winner": "home",
        "date": "2025-09-09"
    },
    {
        "match_id": "zF0rhcfc",
        "tournament": "M15 Haren (Netherlands), clay",
        "ground": "Clay",
        "date_text": "05.09.2025",
        "home_player": "Slump S.",
        "away_player": "Loureiro J. V. C.",
        "home_score": 2,
        "away_score": 1,
        "winner": "home",
        "date": "2025-09-05"
    },
    {
        "match_id": "SbfqHktg",
        "tournament": "M15 Haren (Netherlands), clay",
        "ground": "Clay",
        "date_text": "02.09.2025",
        "home_player": "Loureiro J. V. C.",
        "away_player": "Lipp M.",
        "home_score": 2,
        "away_score": 1,
        "winner": "home",
        "date": "2025-09-02"
    },
    {
        "match_id": "Otn4XbjS",
        "tournament": "M15 Arad (Romania), clay",
        "ground": "Clay",
        "date_text": "21.08.2025",
        "home_player": "Denisov I.",
        "away_player": "Loureiro J. V. C.",
        "home_score": 2,
        "away_score": 1,
        "winner": "home",
        "date": "2025-08-21"
    },
    {
        "match_id": "fZXUkKig",
        "tournament": "M15 Arad (Romania), clay",
        "ground": "Clay",
        "date_text": "19.08.2025",
        "home_player": "Loureiro J. V. C.",
        "away_player": "Gschwendtner J.",
        "home_score": 2,
        "away_score": 1,
        "winner": "home",
        "date": "2025-08-19"
    },
    {
        "match_id": "r3YQYyY2",
        "tournament": "M15 Joinville (Brazil), clay",
        "ground": "Clay",
        "date_text": "01.08.2025",
        "home_player": "Kohlmann E.",
        "away_player": "Loureiro J. V. C.",
        "home_score": 2,
        "away_score": 0,
        "winner": "home",
        "date": "2025-08-01"
    },
    {
        "match_id": "A9dHOZsT",
        "tournament": "M15 Joinville (Brazil), clay",
        "ground": "Clay",
        "date_text": "31.07.2025",
        "home_player": "Loureiro J. V. C.",
        "away_player": "Yamacita F.",
        "home_score": 2,
        "away_score": 0,
        "winner": "home",
        "date": "2025-07-31"
    }
]