[
    {
        "match_id": "x2IFYx4l",
        "tournament": "Brescia (Italy), clay",
        "ground": "Clay",
        "date_text": "16.06. 16:00",
        "home_player": "Kovinic D.",
        "away_player": "Bulgaru M.",
        "home_score": 0,
        "away_score": 2,
        "winner": "away",
        "set_scores": [
            {
                "home": "4",
                "away": "6"
            },
            {
                "home": "3",
                "away": "6"
            }
        ],
        "date": "2026-06-16"
    },
    {
        "match_id": "bq55rYBU",
        "tournament": "Makarska (Croatia), clay",
        "ground": "Clay",
        "date_text": "02.06. 19:15",
        "home_player": "Bulgaru M.",
        "away_player": "Noha Akugue N.",
        "home_score": 0,
        "away_score": 2,
        "winner": "away",
        "set_scores": [
            {
                "home": "6",
                "away": "7"
            },
            {
                "home": "5",
                "away": "7"
            }
        ],
        "date": "2026-06-02"
    },
    {
        "match_id": "nDexLCR0",
        "tournament": "W35 Bol 2 (Croatia), clay",
        "ground": "Clay",
        "date_text": "27.05. 13:10",
        "home_player": "Bulgaru M.",
        "away_player": "Primorac I.",
        "home_score": 1,
        "away_score": 2,
        "winner": "away",
        "set_scores": [
            {
                "home": "6",
                "away": "3"
            },
            {
                "home": "4",
                "away": "6"
            },
            {
                "home": "6",
                "away": "7"
            }
        ],
        "date": "2026-05-27"
    },
    {
        "match_id": "6LCaIyqA",
        "tournament": "French Open (France) - Qualification, clay",
        "ground": "Clay",
        "date_text": "18.05. 11:10",
        "home_player": "Bulgaru M.",
        "away_player": "Guo H.",
        "home_score": 0,
        "away_score": 2,
        "winner": "away",
        "set_scores": [
            {
                "home": "5",
                "away": "7"
            },
            {
                "home": "0",
                "away": "6"
            }
        ],
        "date": "2026-05-18"
    },
    {
        "match_id": "UV3niXDa",
        "tournament": "W75 Trnava 3 (Slovakia), clay",
        "ground": "Clay",
        "date_text": "12.05. 15:35",
        "home_player": "Tan H.",
        "away_player": "Bulgaru M.",
        "home_score": 2,
        "away_score": 0,
        "winner": "home",
        "set_scores": [
            {
                "home": "6",
                "away": "4"
            },
            {
                "home": "6",
                "away": "2"
            }
        ],
        "date": "2026-05-12"
    },
    {
        "match_id": "Wv6R8RMF",
        "tournament": "W75 Saint-Gaudens (France), clay",
        "ground": "Clay",
        "date_text": "06.05. 18:45",
        "home_player": "Belgraver J.",
        "away_player": "Bulgaru M.",
        "home_score": 2,
        "away_score": 0,
        "winner": "home",
        "set_scores": [
            {
                "home": "7",
                "away": "6"
            },
            {
                "home": "7",
                "away": "6"
            }
        ],
        "date": "2026-05-06"
    },
    {
        "match_id": "rPOsAypH",
        "tournament": "W100 Wiesbaden (Germany), clay",
        "ground": "Clay",
        "date_text": "28.04. 17:00",
        "home_player": "Gasanova A.",
        "away_player": "Bulgaru M.",
        "home_score": 2,
        "away_score": 0,
        "winner": "home",
        "set_scores": [
            {
                "home": "6",
                "away": "2"
            },
            {
                "home": "6",
                "away": "2"
            }
        ],
        "date": "2026-04-28"
    },
    {
        "match_id": "vZjpo6eR",
        "tournament": "W75 Chiasso (Switzerland), clay",
        "ground": "Clay",
        "date_text": "22.04. 15:15",
        "home_player": "Bulgaru M.",
        "away_player": "Bonelli E.",
        "home_score": 1,
        "away_score": 2,
        "winner": "away",
        "set_scores": [
            {
                "home": "6",
                "away": "4"
            },
            {
                "home": "2",
                "away": "6"
            },
            {
                "home": "6",
                "away": "7"
            }
        ],
        "date": "2026-04-22"
    },
    {
        "match_id": "xOBkeIpR",
        "tournament": "Cluj-Napoca (Romania), hard (indoor)",
        "ground": "Hard",
        "date_text": "02.02. 14:15",
        "home_player": "Bulgaru M.",
        "away_player": "Danilovic O.",
        "home_score": 0,
        "away_score": 2,
        "winner": "away",
        "set_scores": [
            {
                "home": "4",
                "away": "6"
            },
            {
                "home": "3",
                "away": "6"
            }
        ],
        "date": "2026-02-02"
    },
    {
        "match_id": "thLIn02E",
        "tournament": "W75 Manama (Bahrain), hard",
        "ground": "Hard",
        "date_text": "20.01. 18:50",
        "home_player": "Rosatello C.",
        "away_player": "Bulgaru M.",
        "home_score": 2,
        "away_score": 1,
        "winner": "home",
        "set_scores": [
            {
                "home": "6",
                "away": "2"
            },
            {
                "home": "0",
                "away": "6"
            },
            {
                "home": "6",
                "away": "3"
            }
        ],
        "date": "2026-01-20"
    },
    {
        "match_id": "QqLgwO8c",
        "tournament": "Australian Open (Australia) - Qualification, hard",
        "ground": "Hard",
        "date_text": "13.01. 06:30",
        "home_player": "Korpatsch T.",
        "away_player": "Bulgaru M.",
        "home_score": 2,
        "away_score": 1,
        "winner": "home",
        "set_scores": [
            {
                "home": "6",
                "away": "4"
            },
            {
                "home": "6",
                "away": "7"
            },
            {
                "home": "6",
                "away": "2"
            }
        ],
        "date": "2026-01-13"
    },
    {
        "match_id": "OYViviFq",
        "tournament": "Canberra (Australia) - Qualification, hard",
        "ground": "Hard",
        "date_text": "05.01. 02:40",
        "home_player": "Zidansek T.",
        "away_player": "Bulgaru M.",
        "home_score": 2,
        "away_score": 0,
        "winner": "home",
        "set_scores": [
            {
                "home": "6",
                "away": "2"
            },
            {
                "home": "6",
                "away": "3"
            }
        ],
        "date": "2026-01-05"
    },
    {
        "match_id": "EkZm6Ilm",
        "tournament": "Canberra (Australia) - Qualification, hard",
        "ground": "Hard",
        "date_text": "04.01. 07:20",
        "home_player": "Alame Re.",
        "away_player": "Bulgaru M.",
        "home_score": 0,
        "away_score": 2,
        "winner": "away",
        "set_scores": [
            {
                "home": "1",
                "away": "6"
            },
            {
                "home": "4",
                "away": "6"
            }
        ],
        "date": "2026-01-04"
    },
    {
        "match_id": "CjUsZl0T",
        "tournament": "Quito (Ecuador), clay",
        "ground": "Clay",
        "date_text": "01.12.2025",
        "home_player": "Kalieva E.",
        "away_player": "Bulgaru M.",
        "home_score": 2,
        "away_score": 0,
        "winner": "home",
        "set_scores": [
            {
                "home": "6",
                "away": "3"
            },
            {
                "home": "6",
                "away": "3"
            }
        ],
        "date": "2025-12-01"
    },
    {
        "match_id": "C6An0nmC",
        "tournament": "Buenos Aires (Argentina), clay",
        "ground": "Clay",
        "date_text": "28.11.2025",
        "home_player": "Bulgaru M.",
        "away_player": "Udvardy P.",
        "home_score": 0,
        "away_score": 2,
        "winner": "away",
        "set_scores": [
            {
                "home": "1",
                "away": "6"
            },
            {
                "home": "2",
                "away": "6"
            }
        ],
        "date": "2025-11-28"
    },
    {
        "match_id": "j7KpCTYR",
        "tournament": "Buenos Aires (Argentina), clay",
        "ground": "Clay",
        "date_text": "27.11.2025",
        "home_player": "Carle M. L.",
        "away_player": "Bulgaru M.",
        "home_score": 0,
        "away_score": 2,
        "winner": "away",
        "set_scores": [
            {
                "home": "6",
                "away": "7"
            },
            {
                "home": "3",
                "away": "6"
            }
        ],
        "date": "2025-11-27"
    },
    {
        "match_id": "dMS7wBdE",
        "tournament": "Buenos Aires (Argentina), clay",
        "ground": "Clay",
        "date_text": "25.11.2025",
        "home_player": "Burillo Escorihuela I.",
        "away_player": "Bulgaru M.",
        "home_score": 0,
        "away_score": 2,
        "winner": "away",
        "set_scores": [
            {
                "home": "5",
                "away": "7"
            },
            {
                "home": "0",
                "away": "6"
            }
        ],
        "date": "2025-11-25"
    },
    {
        "match_id": "AJ3oP2Es",
        "tournament": "Colina (Chile), clay",
        "ground": "Clay",
        "date_text": "19.11.2025",
        "home_player": "Bulgaru M.",
        "away_player": "Sherif M.",
        "home_score": 0,
        "away_score": 2,
        "winner": "away",
        "set_scores": [
            {
                "home": "0",
                "away": "6"
            },
            {
                "home": "3",
                "away": "6"
            }
        ],
        "date": "2025-11-19"
    },
    {
        "match_id": "6HTn9dsI",
        "tournament": "Colina (Chile), clay",
        "ground": "Clay",
        "date_text": "17.11.2025",
        "home_player": "Bulgaru M.",
        "away_player": "Akli A.",
        "home_score": 2,
        "away_score": 0,
        "winner": "home",
        "set_scores": [
            {
                "home": "6",
                "away": "4"
            },
            {
                "home": "6",
                "away": "2"
            }
        ],
        "date": "2025-11-17"
    },
    {
        "match_id": "4QpqGS2k",
        "tournament": "Tucuman (Argentina), clay",
        "ground": "Clay",
        "date_text": "05.11.2025",
        "home_player": "Sierra S.",
        "away_player": "Bulgaru M.",
        "home_score": 2,
        "away_score": 0,
        "winner": "home",
        "set_scores": [
            {
                "home": "6",
                "away": "3"
            },
            {
                "home": "7",
                "away": "5"
            }
        ],
        "date": "2025-11-05"
    },
    {
        "match_id": "2yBslZ9U",
        "tournament": "W100 Irapuato (Mexico), hard",
        "ground": "Hard",
        "date_text": "31.10.2025",
        "home_player": "Bulgaru M.",
        "away_player": "Arconada U. M.",
        "home_score": 0,
        "away_score": 2,
        "winner": "away",
        "set_scores": [
            {
                "home": "3",
                "away": "6"
            },
            {
                "home": "5",
                "away": "7"
            }
        ],
        "date": "2025-10-31"
    },
    {
        "match_id": "QoYo2fcn",
        "tournament": "W100 Irapuato (Mexico), hard",
        "ground": "Hard",
        "date_text": "28.10.2025",
        "home_player": "Bulgaru M.",
        "away_player": "Martinez Solis C. S.",
        "home_score": 2,
        "away_score": 0,
        "winner": "home",
        "set_scores": [
            {
                "home": "7",
                "away": "6"
            },
            {
                "home": "6",
                "away": "3"
            }
        ],
        "date": "2025-10-28"
    },
    {
        "match_id": "SOXo3rgC",
        "tournament": "Queretaro (Mexico), clay",
        "ground": "Clay",
        "date_text": "25.10.2025",
        "home_player": "Bulgaru M.",
        "away_player": "Scott K.",
        "home_score": 1,
        "away_score": 2,
        "winner": "away",
        "set_scores": [
            {
                "home": "6",
                "away": "3"
            },
            {
                "home": "6",
                "away": "7"
            },
            {
                "home": "2",
                "away": "6"
            }
        ],
        "date": "2025-10-25"
    },
    {
        "match_id": "AZecermK",
        "tournament": "Queretaro (Mexico), clay",
        "ground": "Clay",
        "date_text": "23.10.2025",
        "home_player": "Bulgaru M.",
        "away_player": "Okalova M.",
        "home_score": 2,
        "away_score": 0,
        "winner": "home",
        "set_scores": [
            {
                "home": "7",
                "away": "6"
            },
            {
                "home": "6",
                "away": "3"
            }
        ],
        "date": "2025-10-23"
    },
    {
        "match_id": "OEy76887",
        "tournament": "Queretaro (Mexico), clay",
        "ground": "Clay",
        "date_text": "21.10.2025",
        "home_player": "Bulgaru M.",
        "away_player": "Navarro M. F.",
        "home_score": 2,
        "away_score": 0,
        "winner": "home",
        "set_scores": [
            {
                "home": "6",
                "away": "2"
            },
            {
                "home": "6",
                "away": "3"
            }
        ],
        "date": "2025-10-21"
    },
    {
        "match_id": "SbpYiS2C",
        "tournament": "Mallorca (Spain), clay",
        "ground": "Clay",
        "date_text": "07.10.2025",
        "home_player": "Radivojevic L.",
        "away_player": "Bulgaru M.",
        "home_score": 2,
        "away_score": 0,
        "winner": "home",
        "set_scores": [
            {
                "home": "6",
                "away": "4"
            },
            {
                "home": "6",
                "away": "3"
            }
        ],
        "date": "2025-10-07"
    },
    {
        "match_id": "E5uyCHUO",
        "tournament": "W75 Bucharest 3 (Romania), clay",
        "ground": "Clay",
        "date_text": "04.10.2025",
        "home_player": "Bulgaru M.",
        "away_player": "Rosatello C.",
        "home_score": 0,
        "away_score": 2,
        "winner": "away",
        "set_scores": [
            {
                "home": "2",
                "away": "6"
            },
            {
                "home": "4",
                "away": "6"
            }
        ],
        "date": "2025-10-04"
    },
    {
        "match_id": "SM2M9CrC",
        "tournament": "W75 Bucharest 3 (Romania), clay",
        "ground": "Clay",
        "date_text": "04.10.2025",
        "home_player": "Bulgaru M.",
        "away_player": "Barbulescu B.",
        "home_score": 2,
        "away_score": 0,
        "winner": "home",
        "set_scores": [
            {
                "home": "6",
                "away": "3"
            },
            {
                "home": "6",
                "away": "2"
            }
        ],
        "date": "2025-10-04"
    },
    {
        "match_id": "CKiAosSs",
        "tournament": "W75 Bucharest 3 (Romania), clay",
        "ground": "Clay",
        "date_text": "30.09.2025",
        "home_player": "Bulgaru M.",
        "away_player": "Yoruk I.",
        "home_score": 2,
        "away_score": 0,
        "winner": "home",
        "set_scores": [
            {
                "home": "6",
                "away": "1"
            },
            {
                "home": "6",
                "away": "4"
            }
        ],
        "date": "2025-09-30"
    },
    {
        "match_id": "UuWHYg3S",
        "tournament": "W50+H Pazardzhik 2 (Bulgaria), clay",
        "ground": "Clay",
        "date_text": "24.09.2025",
        "home_player": "Bulgaru M.",
        "away_player": "Stankovic A.",
        "home_score": 1,
        "away_score": 2,
        "winner": "away",
        "set_scores": [
            {
                "home": "1",
                "away": "6"
            },
            {
                "home": "7",
                "away": "5"
            },
            {
                "home": "6",
                "away": "7"
            }
        ],
        "date": "2025-09-24"
    },
    {
        "match_id": "MuSvSfoC",
        "tournament": "W75 Vienna (Austria), clay",
        "ground": "Clay",
        "date_text": "07.09.2025",
        "home_player": "Bulgaru M.",
        "away_player": "Kraus S.",
        "home_score": 1,
        "away_score": 2,
        "winner": "away",
        "set_scores": [
            {
                "home": "6",
                "away": "3"
            },
            {
                "home": "2",
                "away": "6"
            },
            {
                "home": "3",
                "away": "6"
            }
        ],
        "date": "2025-09-07"
    },
    {
        "match_id": "dAI0ZNog",
        "tournament": "W75 Vienna (Austria), clay",
        "ground": "Clay",
        "date_text": "06.09.2025",
        "home_player": "Bulgaru M.",
        "away_player": "Pircher A.",
        "home_score": 2,
        "away_score": 0,
        "winner": "home",
        "set_scores": [
            {
                "home": "6",
                "away": "1"
            },
            {
                "home": "6",
                "away": "4"
            }
        ],
        "date": "2025-09-06"
    },
    {
        "match_id": "CIS8jfx9",
        "tournament": "W75 Vienna (Austria), clay",
        "ground": "Clay",
        "date_text": "05.09.2025",
        "home_player": "Zavatska K.",
        "away_player": "Bulgaru M.",
        "home_score": 1,
        "away_score": 2,
        "winner": "away",
        "set_scores": [
            {
                "home": "4",
                "away": "6"
            },
            {
                "home": "6",
                "away": "4"
            },
            {
                "home": "4",
                "away": "6"
            }
        ],
        "date": "2025-09-05"
    },
    {
        "match_id": "W2uIAqft",
        "tournament": "W75 Vienna (Austria), clay",
        "ground": "Clay",
        "date_text": "04.09.2025",
        "home_player": "Hietaranta L.",
        "away_player": "Bulgaru M.",
        "home_score": 1,
        "away_score": 2,
        "winner": "away",
        "set_scores": [
            {
                "home": "0",
                "away": "6"
            },
            {
                "home": "7",
                "away": "6"
            },
            {
                "home": "1",
                "away": "6"
            }
        ],
        "date": "2025-09-04"
    },
    {
        "match_id": "ARZ7agkf",
        "tournament": "W75 Vienna (Austria), clay",
        "ground": "Clay",
        "date_text": "03.09.2025",
        "home_player": "Boskovic L.",
        "away_player": "Bulgaru M.",
        "home_score": 0,
        "away_score": 2,
        "winner": "away",
        "set_scores": [
            {
                "home": "5",
                "away": "7"
            },
            {
                "home": "3",
                "away": "6"
            }
        ],
        "date": "2025-09-03"
    },
    {
        "match_id": "UqfT6jUs",
        "tournament": "W50 Bistrita (Romania), clay",
        "ground": "Clay",
        "date_text": "24.08.2025",
        "home_player": "Jorge M.",
        "away_player": "Bulgaru M.",
        "home_score": 0,
        "away_score": 2,
        "winner": "away",
        "set_scores": [
            {
                "home": "0",
                "away": "6"
            },
            {
                "home": "3",
                "away": "6"
            }
        ],
        "date": "2025-08-24"
    },
    {
        "match_id": "ITMiM6c3",
        "tournament": "W50 Bistrita (Romania), clay",
        "ground": "Clay",
        "date_text": "23.08.2025",
        "home_player": "Bulgaru M.",
        "away_player": "In-Albon Y.",
        "home_score": 2,
        "away_score": 0,
        "winner": "home",
        "set_scores": [
            {
                "home": "6",
                "away": "1"
            },
            {
                "home": "6",
                "away": "3"
            }
        ],
        "date": "2025-08-23"
    },
    {
        "match_id": "8Kr2yqU0",
        "tournament": "W50 Bistrita (Romania), clay",
        "ground": "Clay",
        "date_text": "22.08.2025",
        "home_player": "Kazionova E.",
        "away_player": "Bulgaru M.",
        "home_score": 0,
        "away_score": 2,
        "winner": "away",
        "set_scores": [
            {
                "home": "6",
                "away": "7"
            },
            {
                "home": "2",
                "away": "6"
            }
        ],
        "date": "2025-08-22"
    },
    {
        "match_id": "0QgDZP5U",
        "tournament": "W50 Bistrita (Romania), clay",
        "ground": "Clay",
        "date_text": "21.08.2025",
        "home_player": "Popa M. S.",
        "away_player": "Bulgaru M.",
        "home_score": 0,
        "away_score": 2,
        "winner": "away",
        "set_scores": [
            {
                "home": "0",
                "away": "6"
            },
            {
                "home": "4",
                "away": "6"
            }
        ],
        "date": "2025-08-21"
    },
    {
        "match_id": "YaXhNPhT",
        "tournament": "W50 Bistrita (Romania), clay",
        "ground": "Clay",
        "date_text": "20.08.2025",
        "home_player": "Noha Akugue N.",
        "away_player": "Bulgaru M.",
        "home_score": 1,
        "away_score": 2,
        "winner": "away",
        "set_scores": [
            {
                "home": "6",
                "away": "3"
            },
            {
                "home": "3",
                "away": "6"
            },
            {
                "home": "1",
                "away": "6"
            }
        ],
        "date": "2025-08-20"
    },
    {
        "match_id": "fgA9gJ6c",
        "tournament": "W75 Kursumlijska Banja 2 (Serbia), clay",
        "ground": "Clay",
        "date_text": "14.08.2025\nRetired",
        "home_player": "Ristic M.",
        "away_player": "Bulgaru M.",
        "home_score": 1,
        "away_score": 0,
        "winner": "home",
        "set_scores": [
            {
                "home": "6",
                "away": "4"
            },
            {
                "home": "4",
                "away": "2"
            }
        ],
        "date": "2025-08-14"
    },
    {
        "match_id": "zyhWCfqQ",
        "tournament": "W75 Kursumlijska Banja 2 (Serbia), clay",
        "ground": "Clay",
        "date_text": "13.08.2025",
        "home_player": "Paganetti V.",
        "away_player": "Bulgaru M.",
        "home_score": 1,
        "away_score": 2,
        "winner": "away",
        "set_scores": [
            {
                "home": "5",
                "away": "7"
            },
            {
                "home": "7",
                "away": "6"
            },
            {
                "home": "6",
                "away": "7"
            }
        ],
        "date": "2025-08-13"
    },
    {
        "match_id": "AsY3IUHt",
        "tournament": "W35 Kursumlijska Banja 2 (Serbia), clay",
        "ground": "Clay",
        "date_text": "10.08.2025",
        "home_player": "Bulgaru M.",
        "away_player": "Gjorcheska L.",
        "home_score": 2,
        "away_score": 1,
        "winner": "home",
        "set_scores": [
            {
                "home": "5",
                "away": "7"
            },
            {
                "home": "6",
                "away": "1"
            },
            {
                "home": "6",
                "away": "0"
            }
        ],
        "date": "2025-08-10"
    }
]