[
    {
        "match_id": "pIXMlCVq",
        "tournament": "M15 Vaasa (Finland), hard",
        "ground": "Hard",
        "date_text": "12.06.2025",
        "home_player": "Saatela L.",
        "away_player": "Hurrion M.",
        "home_score": 0,
        "away_score": 2,
        "winner": "away",
        "set_scores": [
            {
                "home": "2",
                "away": "6"
            },
            {
                "home": "3",
                "away": "6"
            }
        ],
        "date": "2025-06-12"
    },
    {
        "match_id": "CrKx6DXo",
        "tournament": "M15 Vaasa (Finland), hard",
        "ground": "Hard",
        "date_text": "11.06.2025",
        "home_player": "Saatela L.",
        "away_player": "Hoogland J.",
        "home_score": 2,
        "away_score": 0,
        "winner": "home",
        "set_scores": [
            {
                "home": "6",
                "away": "2"
            },
            {
                "home": "6",
                "away": "4"
            }
        ],
        "date": "2025-06-11"
    },
    {
        "match_id": "hpzwLCKr",
        "tournament": "Helsinki (Finland) - Qualification, hard (indoor)",
        "ground": "Hard",
        "date_text": "05.11.2023",
        "home_player": "Saatela L.",
        "away_player": "Krutykh O.",
        "home_score": 0,
        "away_score": 2,
        "winner": "away",
        "set_scores": [
            {
                "home": "1",
                "away": "6"
            },
            {
                "home": "0",
                "away": "6"
            }
        ],
        "date": "2023-11-05"
    },
    {
        "match_id": "SIAXKBdg",
        "tournament": "Helsinki (Finland), hard (indoor)",
        "ground": "Hard",
        "date_text": "15.11.2022",
        "home_player": "Saatela L.",
        "away_player": "Peniston R.",
        "home_score": 0,
        "away_score": 2,
        "winner": "away",
        "set_scores": [
            {
                "home": "0",
                "away": "6"
            },
            {
                "home": "4",
                "away": "6"
            }
        ],
        "date": "2022-11-15"
    },
    {
        "match_id": "Orm0sRC8",
        "tournament": "M15 Vaasa (Finland), hard",
        "ground": "Hard",
        "date_text": "01.06.2022",
        "home_player": "Vasa E.",
        "away_player": "Saatela L.",
        "home_score": 2,
        "away_score": 0,
        "winner": "home",
        "set_scores": [
            {
                "home": "6",
                "away": "4"
            },
            {
                "home": "6",
                "away": "3"
            }
        ],
        "date": "2022-06-01"
    },
    {
        "match_id": "tOcTDU3K",
        "tournament": "M15 Kouvola (Finland), hard",
        "ground": "Hard",
        "date_text": "19.05.2022",
        "home_player": "Saatela L.",
        "away_player": "Nedelko I.",
        "home_score": 0,
        "away_score": 2,
        "winner": "away",
        "set_scores": [
            {
                "home": "2",
                "away": "6"
            },
            {
                "home": "2",
                "away": "6"
            }
        ],
        "date": "2022-05-19"
    },
    {
        "match_id": "tGwP72J2",
        "tournament": "M15 Kouvola (Finland), hard",
        "ground": "Hard",
        "date_text": "18.05.2022",
        "home_player": "Seeman J.",
        "away_player": "Saatela L.",
        "home_score": 1,
        "away_score": 2,
        "winner": "away",
        "set_scores": [
            {
                "home": "3",
                "away": "6"
            },
            {
                "home": "7",
                "away": "6"
            },
            {
                "home": "3",
                "away": "6"
            }
        ],
        "date": "2022-05-18"
    },
    {
        "match_id": "URnpqWYA",
        "tournament": "M15 Kouvola (Finland), hard",
        "ground": "Hard",
        "date_text": "26.05.2021",
        "home_player": "Saatela L.",
        "away_player": "Tajima N.",
        "home_score": 0,
        "away_score": 2,
        "winner": "away",
        "set_scores": [
            {
                "home": "4",
                "away": "6"
            },
            {
                "home": "2",
                "away": "6"
            }
        ],
        "date": "2021-05-26"
    },
    {
        "match_id": "KnO8945b",
        "tournament": "Helsinki (Finland), hard (indoor)",
        "ground": "Hard",
        "date_text": "12.11.2019",
        "home_player": "Saatela L.",
        "away_player": "Virtanen O.",
        "home_score": 0,
        "away_score": 2,
        "winner": "away",
        "set_scores": [
            {
                "home": "0",
                "away": "6"
            },
            {
                "home": "3",
                "away": "6"
            }
        ],
        "date": "2019-11-12"
    }
]