{
  "game_id": "401320614",
  "date": "2021-06-06",
  "season": 2021,
  "home_team_id": "8",
  "away_team_id": "20",
  "players_by_team": {
    "20": [
      {
        "athlete_id": "2490514",
        "name": "Tianna Hawkins",
        "minutes": 10.0,
        "points": 0
      },
      {
        "athlete_id": "2566081",
        "name": "Elizabeth Williams",
        "minutes": 22.0,
        "points": 5
      },
      {
        "athlete_id": "1054",
        "name": "Tiffany Hayes",
        "minutes": 22.0,
        "points": 21
      },
      {
        "athlete_id": "2529047",
        "name": "Odyssey Sims",
        "minutes": 19.0,
        "points": 0
      },
      {
        "athlete_id": "2987891",
        "name": "Courtney Williams",
        "minutes": 33.0,
        "points": 13
      },
      {
        "athlete_id": "1110",
        "name": "Shekinna Stricklen",
        "minutes": 13.0,
        "points": 0
      },
      {
        "athlete_id": "2529458",
        "name": "Cheyenne Parker-Tyus",
        "minutes": 20.0,
        "points": 12
      },
      {
        "athlete_id": "2591976",
        "name": "Crystal Bradford",
        "minutes": 18.0,
        "points": 12
      },
      {
        "athlete_id": "3142255",
        "name": "Monique Billings",
        "minutes": 20.0,
        "points": 2
      },
      {
        "athlete_id": "4066553",
        "name": "Aari McDonald",
        "minutes": 24.0,
        "points": 15
      },
      {
        "athlete_id": "4280892",
        "name": "Chennedy Carter",
        "minutes": 0.0,
        "points": 0
      }
    ],
    "8": [
      {
        "athlete_id": "3906972",
        "name": "Bridget Carleton",
        "minutes": 33.0,
        "points": 8
      },
      {
        "athlete_id": "3917450",
        "name": "Napheesa Collier",
        "minutes": 33.0,
        "points": 14
      },
      {
        "athlete_id": "766",
        "name": "Sylvia Fowles",
        "minutes": 23.0,
        "points": 17
      },
      {
        "athlete_id": "2490794",
        "name": "Layshia Clarendon",
        "minutes": 21.0,
        "points": 4
      },
      {
        "athlete_id": "2529205",
        "name": "Kayla McBride",
        "minutes": 23.0,
        "points": 19
      },
      {
        "athlete_id": "2529203",
        "name": "Natalie Achonwa",
        "minutes": 22.0,
        "points": 8
      },
      {
        "athlete_id": "3906949",
        "name": "Jessica Shepard",
        "minutes": 4.0,
        "points": 0
      },
      {
        "athlete_id": "2566186",
        "name": "Rachel Banham",
        "minutes": 15.0,
        "points": 13
      },
      {
        "athlete_id": "4066585",
        "name": "Crystal Dangerfield",
        "minutes": 26.0,
        "points": 17
      },
      {
        "athlete_id": "2955898",
        "name": "Damiris Dantas",
        "minutes": 0.0,
        "points": 0
      },
      {
        "athlete_id": "2999035",
        "name": "Aerial Powers",
        "minutes": 0.0,
        "points": 0
      },
      {
        "athlete_id": "4280888",
        "name": "Rennia Davis",
        "minutes": 0.0,
        "points": 0
      }
    ]
  },
  "fetched_at": "2026-06-23T06:25:12.651194+00:00"
}