{
  "game_id": "401230733",
  "date": "2020-07-25",
  "season": 2020,
  "season_type": "unknown",
  "name": "Seattle Storm at New York Liberty",
  "home_team_id": "9",
  "away_team_id": "14",
  "home_team_abbr": "NY",
  "away_team_abbr": "SEA",
  "home_score": 71,
  "away_score": 87,
  "home_box": {
    "FGM": 23,
    "FGA": 66,
    "FG_PCT": 35.0,
    "3PM": 6,
    "3PA": 28,
    "3P_PCT": 21.0,
    "FTM": 19,
    "FTA": 22,
    "FT_PCT": 86.0,
    "REB": 37,
    "OREB": 5,
    "DRB": 32,
    "AST": 14,
    "STL": 5,
    "BLK": 5,
    "TOV": 19,
    "PF": 15,
    "PTS": 71
  },
  "away_box": {
    "FGM": 34,
    "FGA": 77,
    "FG_PCT": 44.0,
    "3PM": 7,
    "3PA": 23,
    "3P_PCT": 30.0,
    "FTM": 12,
    "FTA": 15,
    "FT_PCT": 80.0,
    "REB": 40,
    "OREB": 8,
    "DRB": 32,
    "AST": 16,
    "STL": 15,
    "BLK": 3,
    "TOV": 13,
    "PF": 21,
    "PTS": 87
  },
  "fetched_at": "2026-06-20T16:56:07.739324+00:00",
  "period": 4
}