{
  "game_id": "401736127",
  "date": "2025-05-23",
  "season": 2025,
  "season_type": "unknown",
  "name": "New York Liberty at Chicago Sky",
  "home_team_id": "19",
  "away_team_id": "9",
  "home_team_abbr": "CHI",
  "away_team_abbr": "NY",
  "home_score": 74,
  "away_score": 99,
  "home_box": {
    "FGM": 25,
    "FGA": 69,
    "FG_PCT": 36.0,
    "3PM": 11,
    "3PA": 27,
    "3P_PCT": 41.0,
    "FTM": 13,
    "FTA": 25,
    "FT_PCT": 52.0,
    "REB": 36,
    "OREB": 15,
    "DRB": 21,
    "AST": 16,
    "STL": 9,
    "BLK": 1,
    "TOV": 23,
    "PF": 18,
    "PTS": 74
  },
  "away_box": {
    "FGM": 32,
    "FGA": 58,
    "FG_PCT": 55.0,
    "3PM": 19,
    "3PA": 34,
    "3P_PCT": 56.0,
    "FTM": 16,
    "FTA": 17,
    "FT_PCT": 94.0,
    "REB": 28,
    "OREB": 3,
    "DRB": 25,
    "AST": 25,
    "STL": 12,
    "BLK": 9,
    "TOV": 19,
    "PF": 19,
    "PTS": 99
  },
  "fetched_at": "2026-06-20T17:09:27.674047+00:00",
  "period": 4
}